{
    "version": "0.0.1",
    "architecture": {
        "32bit": {
            "url": "http://github.com/obay/tfsplit/releases/download/v0.0.1/tfsplit_0.0.1_windows_386.tar.gz",
            "bin": [
                "tfsplit.exe"
            ],
            "hash": "99bdbdd13d3105b0ae5d7d1a81855d41d70f85448b349ab74358802f53646ad1"
        },
        "64bit": {
            "url": "http://github.com/obay/tfsplit/releases/download/v0.0.1/tfsplit_0.0.1_windows_amd64.tar.gz",
            "bin": [
                "tfsplit.exe"
            ],
            "hash": "99f1aec0a840233f1a216c99a5c7e5be1c99cf9b334accd5a9bb4a826120d4ee"
        }
    },
    "homepage": "https://github.com/obay/tfsplit",
    "description": "A tool to rename Terraform files accodrind to the resource type and name.",
    "persist": [
        "data",
        "config.toml"
    ],
    "pre_install": [
        "Write-Host 'Running preinstall command'"
    ],
    "post_install": [
        "Write-Host 'Running postinstall command'"
    ]
}